_fast_align_audio.abi3.so
fast_align_audio/__init__.py
fast_align_audio/_alignment_cffi.py
fast_align_audio/alignment.py
fast_align_audio-0.6.0.dist-info/METADATA
fast_align_audio-0.6.0.dist-info/WHEEL
fast_align_audio-0.6.0.dist-info/top_level.txt
fast_align_audio-0.6.0.dist-info/RECORD
fast_align_audio-0.6.0.dist-info/licenses/LICENSE
